{
    "configurations": [
        {
            "name": "Win32",
            "includePath": [
                "${workspaceFolder}/**"
            ],
            "defines": [
                "_DEBUG",
                "UNICODE",
                "_UNICODE",
                "STM32F103xB"
            ],
            "windowsSdkVersion": "8.1",
            "compilerPath": "C:/arm_gcc/bin/arm-none-eabi-gcc.exe",
            "cStandard": "c11",
            "cppStandard": "c++17",
            "intelliSenseMode": "gcc-x86"
        },
        {
            "name": "ARM",
            "includePath": [
                "${workspaceFolder}/**"
            ],
            "defines": [
                "_DEBUG",
                "UNICODE",
                "_UNICODE",
                "STM32F103xB"
            ],
            "windowsSdkVersion": "8.1",
            "compilerPath": "C:/ARM_GCC/bin/arm-none-eabi-gcc.exe",
            "cStandard": "c11",
            "cppStandard": "c++17",
            "intelliSenseMode": "gcc-x86"
        }
    ],
    "version": 4
}